{"nodes": [{"id": "animation_context", "label": "AnimationContext", "file_type": "document", "source_file": "PREMIUM_THEME_GUIDE.md", "source_location": null}, {"id": "card_tilt_3d", "label": "CardTilt3D", "file_type": "document", "source_file": "PREMIUM_THEME_GUIDE.md", "source_location": null}, {"id": "glass_plane", "label": "GlassPlane", "file_type": "document", "source_file": "PREMIUM_THEME_GUIDE.md", "source_location": null}, {"id": "floating_orbs", "label": "FloatingOrbs", "file_type": "document", "source_file": "PREMIUM_THEME_GUIDE.md", "source_location": null}, {"id": "typography_3d", "label": "Typography3D", "file_type": "document", "source_file": "PREMIUM_THEME_GUIDE.md", "source_location": null}, {"id": "parallax_layers", "label": "ParallaxLayers", "file_type": "document", "source_file": "PREMIUM_THEME_GUIDE.md", "source_location": null}, {"id": "animation_toggle", "label": "AnimationToggle", "file_type": "document", "source_file": "PREMIUM_THEME_GUIDE.md", "source_location": null}, {"id": "device_detection", "label": "Device Detection Utility", "file_type": "document", "source_file": "PREMIUM_THEME_GUIDE.md", "source_location": null}, {"id": "animation_helpers", "label": "Animation Helpers", "file_type": "document", "source_file": "PREMIUM_THEME_GUIDE.md", "source_location": null}, {"id": "theme_system", "label": "Light/Dark Theme System", "file_type": "document", "source_file": "PREMIUM_THEME_GUIDE.md", "source_location": null}, {"id": "premium_theme_3d", "label": "Premium Theme & 3D Animation System", "file_type": "document", "source_file": "PREMIUM_THEME_GUIDE.md", "source_location": null}], "edges": [{"source": "ananth_dev_portfolio", "target": "premium_theme_3d", "relation": "references", "confidence": "EXTRACTED", "confidence_score": 1.0, "source_file": "PREMIUM_THEME_GUIDE.md", "weight": 1.0}, {"source": "premium_theme_3d", "target": "animation_context", "relation": "references", "confidence": "EXTRACTED", "confidence_score": 1.0, "source_file": "PREMIUM_THEME_GUIDE.md", "weight": 1.0}, {"source": "premium_theme_3d", "target": "card_tilt_3d", "relation": "references", "confidence": "EXTRACTED", "confidence_score": 1.0, "source_file": "PREMIUM_THEME_GUIDE.md", "weight": 1.0}, {"source": "premium_theme_3d", "target": "glass_plane", "relation": "references", "confidence": "EXTRACTED", "confidence_score": 1.0, "source_file": "PREMIUM_THEME_GUIDE.md", "weight": 1.0}, {"source": "premium_theme_3d", "target": "floating_orbs", "relation": "references", "confidence": "EXTRACTED", "confidence_score": 1.0, "source_file": "PREMIUM_THEME_GUIDE.md", "weight": 1.0}, {"source": "premium_theme_3d", "target": "typography_3d", "relation": "references", "confidence": "EXTRACTED", "confidence_score": 1.0, "source_file": "PREMIUM_THEME_GUIDE.md", "weight": 1.0}, {"source": "premium_theme_3d", "target": "parallax_layers", "relation": "references", "confidence": "EXTRACTED", "confidence_score": 1.0, "source_file": "PREMIUM_THEME_GUIDE.md", "weight": 1.0}, {"source": "premium_theme_3d", "target": "animation_toggle", "relation": "references", "confidence": "EXTRACTED", "confidence_score": 1.0, "source_file": "PREMIUM_THEME_GUIDE.md", "weight": 1.0}, {"source": "premium_theme_3d", "target": "device_detection", "relation": "references", "confidence": "EXTRACTED", "confidence_score": 1.0, "source_file": "PREMIUM_THEME_GUIDE.md", "weight": 1.0}, {"source": "premium_theme_3d", "target": "animation_helpers", "relation": "references", "confidence": "EXTRACTED", "confidence_score": 1.0, "source_file": "PREMIUM_THEME_GUIDE.md", "weight": 1.0}, {"source": "premium_theme_3d", "target": "theme_system", "relation": "references", "confidence": "EXTRACTED", "confidence_score": 1.0, "source_file": "PREMIUM_THEME_GUIDE.md", "weight": 1.0}, {"source": "premium_theme_3d", "target": "three_js", "relation": "references", "confidence": "EXTRACTED", "confidence_score": 1.0, "source_file": "PREMIUM_THEME_GUIDE.md", "weight": 1.0}, {"source": "animation_context", "target": "device_detection", "relation": "references", "confidence": "EXTRACTED", "confidence_score": 1.0, "source_file": "PREMIUM_THEME_GUIDE.md", "weight": 1.0}], "hyperedges": [{"id": "premium_3d_effects", "label": "Premium 3D Effect Components", "nodes": ["card_tilt_3d", "glass_plane", "floating_orbs", "typography_3d", "parallax_layers"], "relation": "form", "confidence": "EXTRACTED", "confidence_score": 1.0, "source_file": "PREMIUM_THEME_GUIDE.md"}, {"id": "animation_system", "label": "Animation System Infrastructure", "nodes": ["animation_context", "animation_toggle", "device_detection", "animation_helpers", "theme_system"], "relation": "form", "confidence": "EXTRACTED", "confidence_score": 1.0, "source_file": "PREMIUM_THEME_GUIDE.md"}]}