{"nodes": [{"id": "e_new_folder_2_ananth_3d_genesis_folio_main_src_components_mobilebottomnav_tsx", "label": "MobileBottomNav.tsx", "file_type": "code", "source_file": "E:\\New folder (2)\\ananth-3d-genesis-folio-main\\src\\components\\MobileBottomNav.tsx", "source_location": "L1"}, {"id": "components_mobilebottomnav_items", "label": "items", "file_type": "code", "source_file": "E:\\New folder (2)\\ananth-3d-genesis-folio-main\\src\\components\\MobileBottomNav.tsx", "source_location": "L7"}, {"id": "components_mobilebottomnav_smoothscrollto", "label": "smoothScrollTo()", "file_type": "code", "source_file": "E:\\New folder (2)\\ananth-3d-genesis-folio-main\\src\\components\\MobileBottomNav.tsx", "source_location": "L16"}, {"id": "components_mobilebottomnav_mobilebottomnav", "label": "MobileBottomNav", "file_type": "code", "source_file": "E:\\New folder (2)\\ananth-3d-genesis-folio-main\\src\\components\\MobileBottomNav.tsx", "source_location": "L31"}], "edges": [{"source": "e_new_folder_2_ananth_3d_genesis_folio_main_src_components_mobilebottomnav_tsx", "target": "react", "relation": "imports_from", "context": "import", "confidence": "EXTRACTED", "source_file": "E:\\New folder (2)\\ananth-3d-genesis-folio-main\\src\\components\\MobileBottomNav.tsx", "source_location": "L1", "weight": 1.0}, {"source": "e_new_folder_2_ananth_3d_genesis_folio_main_src_components_mobilebottomnav_tsx", "target": "react_router_dom", "relation": "imports_from", "context": "import", "confidence": "EXTRACTED", "source_file": "E:\\New folder (2)\\ananth-3d-genesis-folio-main\\src\\components\\MobileBottomNav.tsx", "source_location": "L2", "weight": 1.0}, {"source": "e_new_folder_2_ananth_3d_genesis_folio_main_src_components_mobilebottomnav_tsx", "target": "lucide_react", "relation": "imports_from", "context": "import", "confidence": "EXTRACTED", "source_file": "E:\\New folder (2)\\ananth-3d-genesis-folio-main\\src\\components\\MobileBottomNav.tsx", "source_location": "L3", "weight": 1.0}, {"source": "e_new_folder_2_ananth_3d_genesis_folio_main_src_components_mobilebottomnav_tsx", "target": "e_new_folder_2_ananth_3d_genesis_folio_main_src_hooks_use_mobile_tsx", "relation": "imports_from", "context": "import", "confidence": "EXTRACTED", "source_file": "E:\\New folder (2)\\ananth-3d-genesis-folio-main\\src\\components\\MobileBottomNav.tsx", "source_location": "L4", "weight": 1.0}, {"source": "e_new_folder_2_ananth_3d_genesis_folio_main_src_components_mobilebottomnav_tsx", "target": "hooks_use_mobile_useismobile", "relation": "imports", "context": "import", "confidence": "EXTRACTED", "source_file": "E:\\New folder (2)\\ananth-3d-genesis-folio-main\\src\\components\\MobileBottomNav.tsx", "source_location": "L4", "weight": 1.0}, {"source": "e_new_folder_2_ananth_3d_genesis_folio_main_src_components_mobilebottomnav_tsx", "target": "framer_motion", "relation": "imports_from", "context": "import", "confidence": "EXTRACTED", "source_file": "E:\\New folder (2)\\ananth-3d-genesis-folio-main\\src\\components\\MobileBottomNav.tsx", "source_location": "L5", "weight": 1.0}, {"source": "e_new_folder_2_ananth_3d_genesis_folio_main_src_components_mobilebottomnav_tsx", "target": "components_mobilebottomnav_items", "relation": "contains", "confidence": "EXTRACTED", "source_file": "E:\\New folder (2)\\ananth-3d-genesis-folio-main\\src\\components\\MobileBottomNav.tsx", "source_location": "L7", "weight": 1.0}, {"source": "e_new_folder_2_ananth_3d_genesis_folio_main_src_components_mobilebottomnav_tsx", "target": "components_mobilebottomnav_smoothscrollto", "relation": "contains", "confidence": "EXTRACTED", "source_file": "E:\\New folder (2)\\ananth-3d-genesis-folio-main\\src\\components\\MobileBottomNav.tsx", "source_location": "L16", "weight": 1.0}, {"source": "e_new_folder_2_ananth_3d_genesis_folio_main_src_components_mobilebottomnav_tsx", "target": "components_mobilebottomnav_mobilebottomnav", "relation": "contains", "confidence": "EXTRACTED", "source_file": "E:\\New folder (2)\\ananth-3d-genesis-folio-main\\src\\components\\MobileBottomNav.tsx", "source_location": "L31", "weight": 1.0}, {"source": "components_mobilebottomnav_smoothscrollto", "target": "gsap", "relation": "imports_from", "confidence": "EXTRACTED", "source_file": "E:\\New folder (2)\\ananth-3d-genesis-folio-main\\src\\components\\MobileBottomNav.tsx", "source_location": "L18", "weight": 1.0}, {"source": "components_mobilebottomnav_smoothscrollto", "target": "scrolltoplugin", "relation": "imports_from", "confidence": "EXTRACTED", "source_file": "E:\\New folder (2)\\ananth-3d-genesis-folio-main\\src\\components\\MobileBottomNav.tsx", "source_location": "L19", "weight": 1.0}], "raw_calls": [{"caller_nid": "components_mobilebottomnav_smoothscrollto", "callee": "registerPlugin", "is_member_call": true, "source_file": "E:\\New folder (2)\\ananth-3d-genesis-folio-main\\src\\components\\MobileBottomNav.tsx", "source_location": "L20"}, {"caller_nid": "components_mobilebottomnav_smoothscrollto", "callee": "to", "is_member_call": true, "source_file": "E:\\New folder (2)\\ananth-3d-genesis-folio-main\\src\\components\\MobileBottomNav.tsx", "source_location": "L21"}, {"caller_nid": "components_mobilebottomnav_smoothscrollto", "callee": "scrollTo", "is_member_call": true, "source_file": "E:\\New folder (2)\\ananth-3d-genesis-folio-main\\src\\components\\MobileBottomNav.tsx", "source_location": "L27"}]}