{"nodes": [{"id": "e_new_folder_2_ananth_3d_genesis_folio_main_src_components_blogpost_tsx", "label": "BlogPost.tsx", "file_type": "code", "source_file": "E:\\New folder (2)\\ananth-3d-genesis-folio-main\\src\\components\\BlogPost.tsx", "source_location": "L1"}, {"id": "components_blogpost_blogpostprops", "label": "BlogPostProps", "file_type": "code", "source_file": "E:\\New folder (2)\\ananth-3d-genesis-folio-main\\src\\components\\BlogPost.tsx", "source_location": "L22"}, {"id": "components_blogpost_blogpost", "label": "BlogPost", "file_type": "code", "source_file": "E:\\New folder (2)\\ananth-3d-genesis-folio-main\\src\\components\\BlogPost.tsx", "source_location": "L27"}], "edges": [{"source": "e_new_folder_2_ananth_3d_genesis_folio_main_src_components_blogpost_tsx", "target": "react", "relation": "imports_from", "context": "import", "confidence": "EXTRACTED", "source_file": "E:\\New folder (2)\\ananth-3d-genesis-folio-main\\src\\components\\BlogPost.tsx", "source_location": "L1", "weight": 1.0}, {"source": "e_new_folder_2_ananth_3d_genesis_folio_main_src_components_blogpost_tsx", "target": "framer_motion", "relation": "imports_from", "context": "import", "confidence": "EXTRACTED", "source_file": "E:\\New folder (2)\\ananth-3d-genesis-folio-main\\src\\components\\BlogPost.tsx", "source_location": "L2", "weight": 1.0}, {"source": "e_new_folder_2_ananth_3d_genesis_folio_main_src_components_blogpost_tsx", "target": "lucide_react", "relation": "imports_from", "context": "import", "confidence": "EXTRACTED", "source_file": "E:\\New folder (2)\\ananth-3d-genesis-folio-main\\src\\components\\BlogPost.tsx", "source_location": "L3", "weight": 1.0}, {"source": "e_new_folder_2_ananth_3d_genesis_folio_main_src_components_blogpost_tsx", "target": "e_new_folder_2_ananth_3d_genesis_folio_main_src_lib_supabase_ts", "relation": "imports_from", "context": "import", "confidence": "EXTRACTED", "source_file": "E:\\New folder (2)\\ananth-3d-genesis-folio-main\\src\\components\\BlogPost.tsx", "source_location": "L4", "weight": 1.0}, {"source": "e_new_folder_2_ananth_3d_genesis_folio_main_src_components_blogpost_tsx", "target": "lib_supabase_blogpost", "relation": "imports", "context": "import", "confidence": "EXTRACTED", "source_file": "E:\\New folder (2)\\ananth-3d-genesis-folio-main\\src\\components\\BlogPost.tsx", "source_location": "L4", "weight": 1.0}, {"source": "e_new_folder_2_ananth_3d_genesis_folio_main_src_components_blogpost_tsx", "target": "lib_supabase_blogcomment", "relation": "imports", "context": "import", "confidence": "EXTRACTED", "source_file": "E:\\New folder (2)\\ananth-3d-genesis-folio-main\\src\\components\\BlogPost.tsx", "source_location": "L4", "weight": 1.0}, {"source": "e_new_folder_2_ananth_3d_genesis_folio_main_src_components_blogpost_tsx", "target": "lib_supabase_blogapi", "relation": "imports", "context": "import", "confidence": "EXTRACTED", "source_file": "E:\\New folder (2)\\ananth-3d-genesis-folio-main\\src\\components\\BlogPost.tsx", "source_location": "L4", "weight": 1.0}, {"source": "e_new_folder_2_ananth_3d_genesis_folio_main_src_components_blogpost_tsx", "target": "e_new_folder_2_ananth_3d_genesis_folio_main_src_lib_auth_ts", "relation": "imports_from", "context": "import", "confidence": "EXTRACTED", "source_file": "E:\\New folder (2)\\ananth-3d-genesis-folio-main\\src\\components\\BlogPost.tsx", "source_location": "L5", "weight": 1.0}, {"source": "e_new_folder_2_ananth_3d_genesis_folio_main_src_components_blogpost_tsx", "target": "lib_auth_getuserip", "relation": "imports", "context": "import", "confidence": "EXTRACTED", "source_file": "E:\\New folder (2)\\ananth-3d-genesis-folio-main\\src\\components\\BlogPost.tsx", "source_location": "L5", "weight": 1.0}, {"source": "e_new_folder_2_ananth_3d_genesis_folio_main_src_components_blogpost_tsx", "target": "e_new_folder_2_ananth_3d_genesis_folio_main_src_lib_markdown_ts", "relation": "imports_from", "context": "import", "confidence": "EXTRACTED", "source_file": "E:\\New folder (2)\\ananth-3d-genesis-folio-main\\src\\components\\BlogPost.tsx", "source_location": "L6", "weight": 1.0}, {"source": "e_new_folder_2_ananth_3d_genesis_folio_main_src_components_blogpost_tsx", "target": "lib_markdown_parsemarkdown", "relation": "imports", "context": "import", "confidence": "EXTRACTED", "source_file": "E:\\New folder (2)\\ananth-3d-genesis-folio-main\\src\\components\\BlogPost.tsx", "source_location": "L6", "weight": 1.0}, {"source": "e_new_folder_2_ananth_3d_genesis_folio_main_src_components_blogpost_tsx", "target": "e_new_folder_2_ananth_3d_genesis_folio_main_src_components_ui_button_tsx", "relation": "imports_from", "context": "import", "confidence": "EXTRACTED", "source_file": "E:\\New folder (2)\\ananth-3d-genesis-folio-main\\src\\components\\BlogPost.tsx", "source_location": "L7", "weight": 1.0}, {"source": "e_new_folder_2_ananth_3d_genesis_folio_main_src_components_blogpost_tsx", "target": "ui_button_button", "relation": "imports", "context": "import", "confidence": "EXTRACTED", "source_file": "E:\\New folder (2)\\ananth-3d-genesis-folio-main\\src\\components\\BlogPost.tsx", "source_location": "L7", "weight": 1.0}, {"source": "e_new_folder_2_ananth_3d_genesis_folio_main_src_components_blogpost_tsx", "target": "e_new_folder_2_ananth_3d_genesis_folio_main_src_components_ui_badge_tsx", "relation": "imports_from", "context": "import", "confidence": "EXTRACTED", "source_file": "E:\\New folder (2)\\ananth-3d-genesis-folio-main\\src\\components\\BlogPost.tsx", "source_location": "L8", "weight": 1.0}, {"source": "e_new_folder_2_ananth_3d_genesis_folio_main_src_components_blogpost_tsx", "target": "ui_badge_badge", "relation": "imports", "context": "import", "confidence": "EXTRACTED", "source_file": "E:\\New folder (2)\\ananth-3d-genesis-folio-main\\src\\components\\BlogPost.tsx", "source_location": "L8", "weight": 1.0}, {"source": "e_new_folder_2_ananth_3d_genesis_folio_main_src_components_blogpost_tsx", "target": "e_new_folder_2_ananth_3d_genesis_folio_main_src_components_ui_input_tsx", "relation": "imports_from", "context": "import", "confidence": "EXTRACTED", "source_file": "E:\\New folder (2)\\ananth-3d-genesis-folio-main\\src\\components\\BlogPost.tsx", "source_location": "L9", "weight": 1.0}, {"source": "e_new_folder_2_ananth_3d_genesis_folio_main_src_components_blogpost_tsx", "target": "ui_input_input", "relation": "imports", "context": "import", "confidence": "EXTRACTED", "source_file": "E:\\New folder (2)\\ananth-3d-genesis-folio-main\\src\\components\\BlogPost.tsx", "source_location": "L9", "weight": 1.0}, {"source": "e_new_folder_2_ananth_3d_genesis_folio_main_src_components_blogpost_tsx", "target": "e_new_folder_2_ananth_3d_genesis_folio_main_src_components_ui_textarea_tsx", "relation": "imports_from", "context": "import", "confidence": "EXTRACTED", "source_file": "E:\\New folder (2)\\ananth-3d-genesis-folio-main\\src\\components\\BlogPost.tsx", "source_location": "L10", "weight": 1.0}, {"source": "e_new_folder_2_ananth_3d_genesis_folio_main_src_components_blogpost_tsx", "target": "ui_textarea_textarea", "relation": "imports", "context": "import", "confidence": "EXTRACTED", "source_file": "E:\\New folder (2)\\ananth-3d-genesis-folio-main\\src\\components\\BlogPost.tsx", "source_location": "L10", "weight": 1.0}, {"source": "e_new_folder_2_ananth_3d_genesis_folio_main_src_components_blogpost_tsx", "target": "e_new_folder_2_ananth_3d_genesis_folio_main_src_components_ui_dialog_tsx", "relation": "imports_from", "context": "import", "confidence": "EXTRACTED", "source_file": "E:\\New folder (2)\\ananth-3d-genesis-folio-main\\src\\components\\BlogPost.tsx", "source_location": "L11", "weight": 1.0}, {"source": "e_new_folder_2_ananth_3d_genesis_folio_main_src_components_blogpost_tsx", "target": "ui_dialog_dialog", "relation": "imports", "context": "import", "confidence": "EXTRACTED", "source_file": "E:\\New folder (2)\\ananth-3d-genesis-folio-main\\src\\components\\BlogPost.tsx", "source_location": "L11", "weight": 1.0}, {"source": "e_new_folder_2_ananth_3d_genesis_folio_main_src_components_blogpost_tsx", "target": "ui_dialog_dialogcontent", "relation": "imports", "context": "import", "confidence": "EXTRACTED", "source_file": "E:\\New folder (2)\\ananth-3d-genesis-folio-main\\src\\components\\BlogPost.tsx", "source_location": "L11", "weight": 1.0}, {"source": "e_new_folder_2_ananth_3d_genesis_folio_main_src_components_blogpost_tsx", "target": "ui_dialog_dialogdescription", "relation": "imports", "context": "import", "confidence": "EXTRACTED", "source_file": "E:\\New folder (2)\\ananth-3d-genesis-folio-main\\src\\components\\BlogPost.tsx", "source_location": "L11", "weight": 1.0}, {"source": "e_new_folder_2_ananth_3d_genesis_folio_main_src_components_blogpost_tsx", "target": "ui_dialog_dialogheader", "relation": "imports", "context": "import", "confidence": "EXTRACTED", "source_file": "E:\\New folder (2)\\ananth-3d-genesis-folio-main\\src\\components\\BlogPost.tsx", "source_location": "L11", "weight": 1.0}, {"source": "e_new_folder_2_ananth_3d_genesis_folio_main_src_components_blogpost_tsx", "target": "ui_dialog_dialogtitle", "relation": "imports", "context": "import", "confidence": "EXTRACTED", "source_file": "E:\\New folder (2)\\ananth-3d-genesis-folio-main\\src\\components\\BlogPost.tsx", "source_location": "L11", "weight": 1.0}, {"source": "e_new_folder_2_ananth_3d_genesis_folio_main_src_components_blogpost_tsx", "target": "sonner", "relation": "imports_from", "context": "import", "confidence": "EXTRACTED", "source_file": "E:\\New folder (2)\\ananth-3d-genesis-folio-main\\src\\components\\BlogPost.tsx", "source_location": "L18", "weight": 1.0}, {"source": "e_new_folder_2_ananth_3d_genesis_folio_main_src_components_blogpost_tsx", "target": "e_new_folder_2_ananth_3d_genesis_folio_main_src_lib_utils_ts", "relation": "imports_from", "context": "import", "confidence": "EXTRACTED", "source_file": "E:\\New folder (2)\\ananth-3d-genesis-folio-main\\src\\components\\BlogPost.tsx", "source_location": "L19", "weight": 1.0}, {"source": "e_new_folder_2_ananth_3d_genesis_folio_main_src_components_blogpost_tsx", "target": "lib_utils_cn", "relation": "imports", "context": "import", "confidence": "EXTRACTED", "source_file": "E:\\New folder (2)\\ananth-3d-genesis-folio-main\\src\\components\\BlogPost.tsx", "source_location": "L19", "weight": 1.0}, {"source": "e_new_folder_2_ananth_3d_genesis_folio_main_src_components_blogpost_tsx", "target": "react_helmet_async", "relation": "imports_from", "context": "import", "confidence": "EXTRACTED", "source_file": "E:\\New folder (2)\\ananth-3d-genesis-folio-main\\src\\components\\BlogPost.tsx", "source_location": "L20", "weight": 1.0}, {"source": "e_new_folder_2_ananth_3d_genesis_folio_main_src_components_blogpost_tsx", "target": "components_blogpost_blogpostprops", "relation": "contains", "confidence": "EXTRACTED", "source_file": "E:\\New folder (2)\\ananth-3d-genesis-folio-main\\src\\components\\BlogPost.tsx", "source_location": "L22", "weight": 1.0}, {"source": "e_new_folder_2_ananth_3d_genesis_folio_main_src_components_blogpost_tsx", "target": "components_blogpost_blogpost", "relation": "contains", "confidence": "EXTRACTED", "source_file": "E:\\New folder (2)\\ananth-3d-genesis-folio-main\\src\\components\\BlogPost.tsx", "source_location": "L27", "weight": 1.0}], "raw_calls": []}