{"nodes": [{"id": "e_new_folder_2_ananth_3d_genesis_folio_main_src_components_theme_animationtoggle_tsx", "label": "AnimationToggle.tsx", "file_type": "code", "source_file": "E:\\New folder (2)\\ananth-3d-genesis-folio-main\\src\\components\\theme\\AnimationToggle.tsx", "source_location": "L1"}, {"id": "theme_animationtoggle_animationtoggle", "label": "AnimationToggle()", "file_type": "code", "source_file": "E:\\New folder (2)\\ananth-3d-genesis-folio-main\\src\\components\\theme\\AnimationToggle.tsx", "source_location": "L13"}], "edges": [{"source": "e_new_folder_2_ananth_3d_genesis_folio_main_src_components_theme_animationtoggle_tsx", "target": "lucide_react", "relation": "imports_from", "context": "import", "confidence": "EXTRACTED", "source_file": "E:\\New folder (2)\\ananth-3d-genesis-folio-main\\src\\components\\theme\\AnimationToggle.tsx", "source_location": "L1", "weight": 1.0}, {"source": "e_new_folder_2_ananth_3d_genesis_folio_main_src_components_theme_animationtoggle_tsx", "target": "e_new_folder_2_ananth_3d_genesis_folio_main_src_components_ui_button_tsx", "relation": "imports_from", "context": "import", "confidence": "EXTRACTED", "source_file": "E:\\New folder (2)\\ananth-3d-genesis-folio-main\\src\\components\\theme\\AnimationToggle.tsx", "source_location": "L2", "weight": 1.0}, {"source": "e_new_folder_2_ananth_3d_genesis_folio_main_src_components_theme_animationtoggle_tsx", "target": "ui_button_button", "relation": "imports", "context": "import", "confidence": "EXTRACTED", "source_file": "E:\\New folder (2)\\ananth-3d-genesis-folio-main\\src\\components\\theme\\AnimationToggle.tsx", "source_location": "L2", "weight": 1.0}, {"source": "e_new_folder_2_ananth_3d_genesis_folio_main_src_components_theme_animationtoggle_tsx", "target": "e_new_folder_2_ananth_3d_genesis_folio_main_src_components_ui_dropdown_menu_tsx", "relation": "imports_from", "context": "import", "confidence": "EXTRACTED", "source_file": "E:\\New folder (2)\\ananth-3d-genesis-folio-main\\src\\components\\theme\\AnimationToggle.tsx", "source_location": "L3", "weight": 1.0}, {"source": "e_new_folder_2_ananth_3d_genesis_folio_main_src_components_theme_animationtoggle_tsx", "target": "ui_dropdown_menu_dropdownmenu", "relation": "imports", "context": "import", "confidence": "EXTRACTED", "source_file": "E:\\New folder (2)\\ananth-3d-genesis-folio-main\\src\\components\\theme\\AnimationToggle.tsx", "source_location": "L3", "weight": 1.0}, {"source": "e_new_folder_2_ananth_3d_genesis_folio_main_src_components_theme_animationtoggle_tsx", "target": "ui_dropdown_menu_dropdownmenucontent", "relation": "imports", "context": "import", "confidence": "EXTRACTED", "source_file": "E:\\New folder (2)\\ananth-3d-genesis-folio-main\\src\\components\\theme\\AnimationToggle.tsx", "source_location": "L3", "weight": 1.0}, {"source": "e_new_folder_2_ananth_3d_genesis_folio_main_src_components_theme_animationtoggle_tsx", "target": "ui_dropdown_menu_dropdownmenuitem", "relation": "imports", "context": "import", "confidence": "EXTRACTED", "source_file": "E:\\New folder (2)\\ananth-3d-genesis-folio-main\\src\\components\\theme\\AnimationToggle.tsx", "source_location": "L3", "weight": 1.0}, {"source": "e_new_folder_2_ananth_3d_genesis_folio_main_src_components_theme_animationtoggle_tsx", "target": "ui_dropdown_menu_dropdownmenutrigger", "relation": "imports", "context": "import", "confidence": "EXTRACTED", "source_file": "E:\\New folder (2)\\ananth-3d-genesis-folio-main\\src\\components\\theme\\AnimationToggle.tsx", "source_location": "L3", "weight": 1.0}, {"source": "e_new_folder_2_ananth_3d_genesis_folio_main_src_components_theme_animationtoggle_tsx", "target": "ui_dropdown_menu_dropdownmenuseparator", "relation": "imports", "context": "import", "confidence": "EXTRACTED", "source_file": "E:\\New folder (2)\\ananth-3d-genesis-folio-main\\src\\components\\theme\\AnimationToggle.tsx", "source_location": "L3", "weight": 1.0}, {"source": "e_new_folder_2_ananth_3d_genesis_folio_main_src_components_theme_animationtoggle_tsx", "target": "ui_dropdown_menu_dropdownmenulabel", "relation": "imports", "context": "import", "confidence": "EXTRACTED", "source_file": "E:\\New folder (2)\\ananth-3d-genesis-folio-main\\src\\components\\theme\\AnimationToggle.tsx", "source_location": "L3", "weight": 1.0}, {"source": "e_new_folder_2_ananth_3d_genesis_folio_main_src_components_theme_animationtoggle_tsx", "target": "e_new_folder_2_ananth_3d_genesis_folio_main_src_contexts_animationcontext_tsx", "relation": "imports_from", "context": "import", "confidence": "EXTRACTED", "source_file": "E:\\New folder (2)\\ananth-3d-genesis-folio-main\\src\\components\\theme\\AnimationToggle.tsx", "source_location": "L11", "weight": 1.0}, {"source": "e_new_folder_2_ananth_3d_genesis_folio_main_src_components_theme_animationtoggle_tsx", "target": "contexts_animationcontext_useanimationpreference", "relation": "imports", "context": "import", "confidence": "EXTRACTED", "source_file": "E:\\New folder (2)\\ananth-3d-genesis-folio-main\\src\\components\\theme\\AnimationToggle.tsx", "source_location": "L11", "weight": 1.0}, {"source": "e_new_folder_2_ananth_3d_genesis_folio_main_src_components_theme_animationtoggle_tsx", "target": "theme_animationtoggle_animationtoggle", "relation": "contains", "confidence": "EXTRACTED", "source_file": "E:\\New folder (2)\\ananth-3d-genesis-folio-main\\src\\components\\theme\\AnimationToggle.tsx", "source_location": "L13", "weight": 1.0}], "raw_calls": [{"caller_nid": "theme_animationtoggle_animationtoggle", "callee": "useAnimationPreference", "is_member_call": false, "source_file": "E:\\New folder (2)\\ananth-3d-genesis-folio-main\\src\\components\\theme\\AnimationToggle.tsx", "source_location": "L14"}, {"caller_nid": "theme_animationtoggle_animationtoggle", "callee": "getLabel", "is_member_call": false, "source_file": "E:\\New folder (2)\\ananth-3d-genesis-folio-main\\src\\components\\theme\\AnimationToggle.tsx", "source_location": "L35"}, {"caller_nid": "theme_animationtoggle_animationtoggle", "callee": "getIcon", "is_member_call": false, "source_file": "E:\\New folder (2)\\ananth-3d-genesis-folio-main\\src\\components\\theme\\AnimationToggle.tsx", "source_location": "L37"}]}